circleapi/__init__.py
circleapi/api.py
circleapi/async_api.py
circleapi/async_token.py
circleapi/logger.py
circleapi/models.py
circleapi/token.py
circleapi/utils.py
circleapi-2024.1.6.1.dist-info/LICENCE
circleapi-2024.1.6.1.dist-info/METADATA
circleapi-2024.1.6.1.dist-info/WHEEL
circleapi-2024.1.6.1.dist-info/top_level.txt
circleapi-2024.1.6.1.dist-info/RECORD
