Metadata-Version: 2.1
Name: circleapi
Version: 2024.1.6.1
Summary: Unoffical osu! apiv2 python wrapper
Author: miinorii
Project-URL: Homepage, https://github.com/miinorii/circleapi
Project-URL: Issues, https://github.com/miinorii/circleapi/issues
Keywords: osu!,apiv2,wrapper
Classifier: Programming Language :: Python :: 3
Classifier: License :: OSI Approved :: MIT License
Classifier: Operating System :: OS Independent
Requires-Python: >=3.10
License-File: LICENCE
Requires-Dist: httpx[http2] ==0.25.2
Requires-Dist: msgspec ==0.18.5
Requires-Dist: python-dotenv ==1.0.0
